nonebot_plugin_nonechat/__init__.py
nonebot_plugin_nonechat/chat.py
nonebot_plugin_nonechat/config.py
nonebot_plugin_nonechat/utils/constants.py
nonebot_plugin_nonechat/utils/llm.py
nonebot_plugin_nonechat/utils/parsers.py
nonebot_plugin_nonechat-0.1.2.dist-info/LICENSE
nonebot_plugin_nonechat-0.1.2.dist-info/METADATA
nonebot_plugin_nonechat-0.1.2.dist-info/WHEEL
nonebot_plugin_nonechat-0.1.2.dist-info/top_level.txt
nonebot_plugin_nonechat-0.1.2.dist-info/RECORD
