Metadata-Version: 2.1
Name: nonebot-plugin-nonechat
Version: 0.1.2
Summary: Add your description here
Requires-Python: <4.0,>=3.9
License-File: LICENSE
Requires-Dist: httpx >=0.27.2
Requires-Dist: langchain-core >=0.3.6
Requires-Dist: langchain-openai >=0.2.1
Requires-Dist: langgraph-checkpoint-sqlite >=1.0.4
Requires-Dist: langgraph >=0.2.28
Requires-Dist: nonebot-plugin-alconna >=0.52.3
Requires-Dist: nonebot-plugin-htmlrender >=0.3.5
Requires-Dist: nonebot-plugin-localstore >=0.7.1
Requires-Dist: nonebot2 >=2.3.3
Requires-Dist: pydantic <3.0.0,>=1.0
